punyverse/__init__.py
punyverse/__main__.py
punyverse/_glgeom.cp37-win32.pyd
punyverse/camera.py
punyverse/entity.py
punyverse/glgeom.py
punyverse/launcher.exe
punyverse/launcher.py
punyverse/launcherw.exe
punyverse/loader.py
punyverse/main.py
punyverse/model.py
punyverse/orbit.py
punyverse/shader.py
punyverse/small_images.py
punyverse/texture.py
punyverse/ui.py
punyverse/utils.py
punyverse/world.json
punyverse/world.py
punyverse/assets/textures.txt
punyverse/assets/models/asteroids/01.obj
punyverse/assets/models/asteroids/02.obj
punyverse/assets/models/asteroids/03.obj
punyverse/assets/models/asteroids/asteroid.mtl
punyverse/assets/models/asteroids/mainbelt.mtl
punyverse/assets/models/asteroids/mainbelt.obj
punyverse/assets/models/asteroids/mainbelt2.obj
punyverse/assets/models/satellites/cassini.mtl
punyverse/assets/models/satellites/cassini.obj
punyverse/assets/models/satellites/hbltel_1.jpg
punyverse/assets/models/satellites/hbltel_2.jpg
punyverse/assets/models/satellites/hbltel_3.jpg
punyverse/assets/models/satellites/hbltel_4.jpg
punyverse/assets/models/satellites/hbltel_w.jpg
punyverse/assets/models/satellites/hst.mtl
punyverse/assets/models/satellites/hst.obj
punyverse/assets/models/satellites/iss.mtl
punyverse/assets/models/satellites/iss.obj
punyverse/assets/models/satellites/phobos.jpg
punyverse/assets/models/satellites/phobos.mtl
punyverse/assets/models/satellites/phobos.obj
punyverse/assets/models/satellites/cassini/foil.jpg
punyverse/assets/models/satellites/cassini/tex.jpg
punyverse/assets/textures/cloudmap.jpg
punyverse/assets/textures/constellation_nx.png
punyverse/assets/textures/constellation_ny.png
punyverse/assets/textures/constellation_nz.png
punyverse/assets/textures/constellation_px.png
punyverse/assets/textures/constellation_py.png
punyverse/assets/textures/constellation_pz.png
punyverse/assets/textures/earth.jpg
punyverse/assets/textures/earth_emission.jpg
punyverse/assets/textures/earth_normal.jpg
punyverse-1.2.dist-info/LICENSE
punyverse-1.2.dist-info/METADATA
punyverse-1.2.dist-info/WHEEL
punyverse-1.2.dist-info/entry_points.txt
punyverse-1.2.dist-info/top_level.txt
punyverse-1.2.dist-info/RECORD
